ink_cms/__init__.py
ink_cms/actions.py
ink_cms/admin.py
ink_cms/api.py
ink_cms/apps.py
ink_cms/asgi.py
ink_cms/config.py
ink_cms/dev_urls.py
ink_cms/errors.py
ink_cms/examples.py
ink_cms/forms.py
ink_cms/history.py
ink_cms/image.py
ink_cms/management/commands/initial_data.py
ink_cms/migrations/0001_initial.py
ink_cms/migrations/__init__.py
ink_cms/models.py
ink_cms/pagination.py
ink_cms/parsers.py
ink_cms/serializers.py
ink_cms/settings.py
ink_cms/static/ink_cms/admin/css/modified_base.css
ink_cms/static/ink_cms/assets/sample.jpg
ink_cms/static/ink_cms/dist/assets/css/app.css
ink_cms/static/ink_cms/dist/assets/css/editor.css
ink_cms/static/ink_cms/dist/assets/fonts/Roboto-Black.woff
ink_cms/static/ink_cms/dist/assets/fonts/Roboto-Black.woff2
ink_cms/static/ink_cms/dist/assets/fonts/Roboto-BlackItalic.woff
ink_cms/static/ink_cms/dist/assets/fonts/Roboto-BlackItalic.woff2
ink_cms/static/ink_cms/dist/assets/fonts/Roboto-Bold.woff
ink_cms/static/ink_cms/dist/assets/fonts/Roboto-Bold.woff2
ink_cms/static/ink_cms/dist/assets/fonts/Roboto-BoldItalic.woff
ink_cms/static/ink_cms/dist/assets/fonts/Roboto-BoldItalic.woff2
ink_cms/static/ink_cms/dist/assets/fonts/Roboto-Light.woff
ink_cms/static/ink_cms/dist/assets/fonts/Roboto-Light.woff2
ink_cms/static/ink_cms/dist/assets/fonts/Roboto-LightItalic.woff
ink_cms/static/ink_cms/dist/assets/fonts/Roboto-LightItalic.woff2
ink_cms/static/ink_cms/dist/assets/fonts/Roboto-Medium.woff
ink_cms/static/ink_cms/dist/assets/fonts/Roboto-Medium.woff2
ink_cms/static/ink_cms/dist/assets/fonts/Roboto-MediumItalic.woff
ink_cms/static/ink_cms/dist/assets/fonts/Roboto-MediumItalic.woff2
ink_cms/static/ink_cms/dist/assets/fonts/Roboto-Regular.woff
ink_cms/static/ink_cms/dist/assets/fonts/Roboto-Regular.woff2
ink_cms/static/ink_cms/dist/assets/fonts/Roboto-RegularItalic.woff
ink_cms/static/ink_cms/dist/assets/fonts/Roboto-RegularItalic.woff2
ink_cms/static/ink_cms/dist/assets/fonts/Roboto-Thin.woff
ink_cms-0.2.0.dist-info/WHEEL
ink_cms-0.2.0.dist-info/METADATA
ink_cms-0.2.0.dist-info/RECORD
