Metadata-Version: 2.1
Name: ink-cms
Version: 0.2.0
Summary: A headless CMS for the Django Admin
License: MIT
Author: Robert Townley
Requires-Python: >=3.6,<4.0
Classifier: License :: OSI Approved :: MIT License
Classifier: Programming Language :: Python :: 3
Classifier: Programming Language :: Python :: 3.6
Classifier: Programming Language :: Python :: 3.7
Classifier: Programming Language :: Python :: 3.8
Requires-Dist: django (>=3.0.2,<4.0.0)
Requires-Dist: djangorestframework (>=3.11.0,<4.0.0)
Requires-Dist: easy-thumbnails (>=2.7,<3.0)
Requires-Dist: psycopg2 (>=2.8.4,<3.0.0)
